README.md
setup.py
iqoption.egg-info/PKG-INFO
iqoption.egg-info/SOURCES.txt
iqoption.egg-info/dependency_links.txt
iqoption.egg-info/not-zip-safe
iqoption.egg-info/requires.txt
iqoption.egg-info/top_level.txt
iqoptionapi/__init__.py
iqoptionapi/api.py
iqoptionapi/constants.py
iqoptionapi/country_id.py
iqoptionapi/expiration.py
iqoptionapi/global_value.py
iqoptionapi/stable_api.py
iqoptionapi/http/__init__.py
iqoptionapi/http/appinit.py
iqoptionapi/http/auth.py
iqoptionapi/http/billing.py
iqoptionapi/http/buyback.py
iqoptionapi/http/changebalance.py
iqoptionapi/http/events.py
iqoptionapi/http/getprofile.py
iqoptionapi/http/getregdata.py
iqoptionapi/http/login.py
iqoptionapi/http/loginv2.py
iqoptionapi/http/logout.py
iqoptionapi/http/profile.py
iqoptionapi/http/register.py
iqoptionapi/http/resource.py
iqoptionapi/http/token.py
iqoptionapi/ws/__init__.py
iqoptionapi/ws/client.py
iqoptionapi/ws/chanels/__init__.py
iqoptionapi/ws/chanels/api_game_betinfo.py
iqoptionapi/ws/chanels/api_game_getoptions.py
iqoptionapi/ws/chanels/base.py
iqoptionapi/ws/chanels/buy_place_order_temp.py
iqoptionapi/ws/chanels/buyback.py
iqoptionapi/ws/chanels/buyv2.py
iqoptionapi/ws/chanels/buyv3.py
iqoptionapi/ws/chanels/cancel_order.py
iqoptionapi/ws/chanels/candles.py
iqoptionapi/ws/chanels/change_auto_margin_call.py
iqoptionapi/ws/chanels/change_tpsl.py
iqoptionapi/ws/chanels/changebalance.py
iqoptionapi/ws/chanels/close_position.py
iqoptionapi/ws/chanels/digital_option.py
iqoptionapi/ws/chanels/get_available_leverages.py
iqoptionapi/ws/chanels/get_balances.py
iqoptionapi/ws/chanels/get_deferred_orders.py
iqoptionapi/ws/chanels/get_financial_information.py
iqoptionapi/ws/chanels/get_order.py
iqoptionapi/ws/chanels/get_overnight_fee.py
iqoptionapi/ws/chanels/get_positions.py
iqoptionapi/ws/chanels/heartbeat.py
iqoptionapi/ws/chanels/instruments.py
iqoptionapi/ws/chanels/leaderboard.py
iqoptionapi/ws/chanels/sell_option.py
iqoptionapi/ws/chanels/setactives.py
iqoptionapi/ws/chanels/ssid.py
iqoptionapi/ws/chanels/strike_list.py
iqoptionapi/ws/chanels/subscribe.py
iqoptionapi/ws/chanels/traders_mood.py
iqoptionapi/ws/chanels/unsubscribe.py
iqoptionapi/ws/chanels/user.py
