Metadata-Version: 1.0
Name: iqoption
Version: 6.8.9.1
Summary: Best IQ Option API for python
Home-page: https://github.com/Lu-Yi-Hsun/iqoptionapi
Author: Lu-Yi-Hsun
Author-email: yihsun1992@gmail.com
License: UNKNOWN
Platform: UNKNOWN
